caeli/__init__.py
caeli/distributions.py
caeli/drought_indices.py
caeli/time_series.py
doc/__init__.py
doc/conf.py
test/02_calculate_spei.py
test/__init__.py
test/doc_examples.py
test/test_caeli.py
caeli-0.0.1.dist-info/LICENSE
caeli-0.0.1.dist-info/METADATA
caeli-0.0.1.dist-info/WHEEL
caeli-0.0.1.dist-info/top_level.txt
caeli-0.0.1.dist-info/RECORD
