Metadata-Version: 2.1
Name: caeli
Version: 0.0.1
Summary: caeli
Home-page: UNKNOWN
Author: Jackson Roehrig
Author-email: Jackson.Roehrig@th-koeln.de
Maintainer: Jackson.Roehrig@th-koeln.de
License: MIT
Download-URL: https://github.com/JRoehrig/caeli
Platform: UNKNOWN
Classifier: Development Status :: 4 - Beta
Classifier: Environment :: Console
Classifier: Intended Audience :: Science/Research
Classifier: License :: OSI Approved :: MIT License
Classifier: Natural Language :: English
Classifier: Operating System :: OS Independent
Classifier: Programming Language :: Python :: 3
Classifier: Topic :: Scientific/Engineering :: Hydrology
Requires-Dist: python-dateutil
Requires-Dist: numpy
Requires-Dist: scipy
Requires-Dist: pandas
